Metadata-Version: 2.1
Name: credints
Version: 0.1
Summary: utility functions for creating credible intervals in pymc and sympy.stats (and possibly others)
Home-page: https://github.com/micklat/credints
Author: Michael Latowicki
License: BSD 3-clause
Classifier: Development Status :: 3 - Alpha
Classifier: Intended Audience :: Science/Research
Classifier: License :: OSI Approved :: BSD License
Classifier: Operating System :: POSIX :: Linux
Classifier: Programming Language :: Python :: 3
Classifier: Programming Language :: Python :: 3.10
